RedisShujukuXuexiJiaochengCYuyanBianchengWang/README.md
RedisShujukuXuexiJiaochengCYuyanBianchengWang/__init__.py
RedisShujukuXuexiJiaochengCYuyanBianchengWang/__main__.py
RedisShujukuXuexiJiaochengCYuyanBianchengWang/file.epub
RedisShujukuXuexiJiaochengCYuyanBianchengWang/index.html
RedisShujukuXuexiJiaochengCYuyanBianchengWang/css/__init__.py
RedisShujukuXuexiJiaochengCYuyanBianchengWang/css/annotations.css
RedisShujukuXuexiJiaochengCYuyanBianchengWang/css/main.css
RedisShujukuXuexiJiaochengCYuyanBianchengWang/css/normalize.css
RedisShujukuXuexiJiaochengCYuyanBianchengWang/css/popup.css
RedisShujukuXuexiJiaochengCYuyanBianchengWang/font/__init__.py
RedisShujukuXuexiJiaochengCYuyanBianchengWang/font/fontello.eot
RedisShujukuXuexiJiaochengCYuyanBianchengWang/font/fontello.svg
RedisShujukuXuexiJiaochengCYuyanBianchengWang/font/fontello.ttf
RedisShujukuXuexiJiaochengCYuyanBianchengWang/font/fontello.woff
RedisShujukuXuexiJiaochengCYuyanBianchengWang/img/__init__.py
RedisShujukuXuexiJiaochengCYuyanBianchengWang/img/annotator-glyph-sprite.png
RedisShujukuXuexiJiaochengCYuyanBianchengWang/img/annotator-icon-sprite.png
RedisShujukuXuexiJiaochengCYuyanBianchengWang/img/apple-touch-icon.png
RedisShujukuXuexiJiaochengCYuyanBianchengWang/img/cancelfullscreen.png
RedisShujukuXuexiJiaochengCYuyanBianchengWang/img/close.png
RedisShujukuXuexiJiaochengCYuyanBianchengWang/img/fullscreen.png
RedisShujukuXuexiJiaochengCYuyanBianchengWang/img/loader.gif
RedisShujukuXuexiJiaochengCYuyanBianchengWang/img/menu-icon.png
RedisShujukuXuexiJiaochengCYuyanBianchengWang/img/save.png
RedisShujukuXuexiJiaochengCYuyanBianchengWang/img/saved.png
RedisShujukuXuexiJiaochengCYuyanBianchengWang/img/settings-s.png
RedisShujukuXuexiJiaochengCYuyanBianchengWang/img/settings.png
RedisShujukuXuexiJiaochengCYuyanBianchengWang/img/star.png
RedisShujukuXuexiJiaochengCYuyanBianchengWang/js/__init__.py
RedisShujukuXuexiJiaochengCYuyanBianchengWang/js/epub.js
redis_shujuku_xuexi_jiaocheng_c_yuyan_biancheng_wang-2024.3.5.0.dist-info/METADATA
redis_shujuku_xuexi_jiaocheng_c_yuyan_biancheng_wang-2024.3.5.0.dist-info/WHEEL
redis_shujuku_xuexi_jiaocheng_c_yuyan_biancheng_wang-2024.3.5.0.dist-info/entry_points.txt
redis_shujuku_xuexi_jiaocheng_c_yuyan_biancheng_wang-2024.3.5.0.dist-info/top_level.txt
redis_shujuku_xuexi_jiaocheng_c_yuyan_biancheng_wang-2024.3.5.0.dist-info/RECORD
